.gitignore
AUTHORS
CHANGES
README
development.ini
setup.py
docs/.gitignore
docs/Makefile
docs/conf.py
docs/index.rst
docs/_static/.gitignore
docs/_templates/.gitignore
kotti_velruse/__init__.py
kotti_velruse/events.py
kotti_velruse/tests.py
kotti_velruse/views.py
kotti_velruse.egg-info/PKG-INFO
kotti_velruse.egg-info/SOURCES.txt
kotti_velruse.egg-info/dependency_links.txt
kotti_velruse.egg-info/not-zip-safe
kotti_velruse.egg-info/requires.txt
kotti_velruse.egg-info/top_level.txt
kotti_velruse/templates/login.mako