Metadata-Version: 1.1
Name: kotti-velruse
Version: 0.3.4
Summary: Kotti authentication with Velruse: OpenID, OAuth2, Google, Yahoo, Live, Facebook, Twitter and others
Home-page: http://kotti_velruse.readthedocs.org
Author: Richard Gomes
Author-email: rgomes.info@gmail.com
License: BSD
Keywords: pyramid kotti authentication velruse openid oauth2 google yahoo live facebook twitter
Platform: UNKNOWN
Classifier: Environment :: Web Environment
Classifier: Framework :: Pylons
Classifier: Framework :: Pyramid
Classifier: Intended Audience :: Developers
Classifier: License :: OSI Approved :: BSD License
Classifier: Operating System :: OS Independent
Classifier: Programming Language :: Python
Classifier: Programming Language :: Python :: 2.6
Classifier: Programming Language :: Python :: 2.7
Classifier: Topic :: Internet :: WWW/HTTP
Classifier: Topic :: Internet :: WWW/HTTP :: Dynamic Content
Classifier: Topic :: Internet :: WWW/HTTP :: WSGI :: Application
Classifier: Topic :: Software Development :: User Interfaces
